appxploit/__init__.py
appxploit/__main__.py
appxploit/analysis/__init__.py
appxploit/analysis/components.py
appxploit/analysis/deeplink_analyzer.py
appxploit/analysis/manifest.py
appxploit/analysis/permissions.py
appxploit/analysis/security_flags.py
appxploit/core/__init__.py
appxploit/core/cli.py
appxploit/core/config.py
appxploit/core/orchestrator.py
appxploit/core/utils.py
appxploit/data/advanced_patterns.yaml
appxploit/data/patterns.yaml
appxploit/data/vuln_rules.yaml
appxploit/discovery/__init__.py
appxploit/discovery/endpoints.py
appxploit/discovery/secrets.py
appxploit/filtering/__init__.py
appxploit/filtering/filter.py
appxploit/filtering/quality_control.py
appxploit/intelligence/__init__.py
appxploit/intelligence/classifier.py
appxploit/intelligence/fingerprint.py
appxploit/intelligence/risk_estimator.py
appxploit/reasoning/__init__.py
appxploit/reasoning/advanced_detector.py
appxploit/reasoning/business_logic.py
appxploit/reasoning/crypto_analyzer.py
appxploit/reasoning/detector.py
appxploit/reasoning/exploits.py
appxploit/reasoning/idor_detector.py
appxploit/reasoning/path_ranker.py
appxploit/reasoning/scorer.py
appxploit/reporting/__init__.py
appxploit/reporting/generator.py
appxploit-1.0.1.dist-info/licenses/LICENSE
appxploit-1.0.1.dist-info/METADATA
appxploit-1.0.1.dist-info/WHEEL
appxploit-1.0.1.dist-info/entry_points.txt
appxploit-1.0.1.dist-info/top_level.txt
appxploit-1.0.1.dist-info/RECORD
