Metadata-Version: 2.4
Name: appxploit
Version: 1.0.1
Summary: Professional Android APK security analysis tool for bug bounty hunters
Home-page: https://github.com/letchupkt/AppXploit
Author: LAKSHMIKANTHAN K
Author-email: 
License: MIT
Project-URL: Homepage, https://github.com/letchupkt/AppXploit
Project-URL: Repository, https://github.com/letchupkt/AppXploit
Project-URL: Issues, https://github.com/letchupkt/AppXploit/issues
Keywords: android,apk,security,analysis,bug-bounty,penetration-testing
Classifier: Development Status :: 4 - Beta
Classifier: Intended Audience :: Developers
Classifier: Intended Audience :: Information Technology
Classifier: Topic :: Security
Classifier: License :: OSI Approved :: MIT License
Classifier: Programming Language :: Python :: 3
Classifier: Programming Language :: Python :: 3.8
Classifier: Programming Language :: Python :: 3.9
Classifier: Programming Language :: Python :: 3.10
Classifier: Programming Language :: Python :: 3.11
Requires-Python: >=3.8
License-File: LICENSE
Requires-Dist: click>=8.1.0
Requires-Dist: colorama>=0.4.6
Requires-Dist: pyyaml>=6.0
Requires-Dist: jinja2>=3.1.2
Requires-Dist: requests>=2.31.0
Requires-Dist: lxml>=4.9.0
Dynamic: home-page
Dynamic: license-file
Dynamic: requires-python
